pyttop/__init__.py
pyttop/config.py
pyttop/matcher.py
pyttop/utils.py
pyttop/plot/__init__.py
pyttop/plot/base.py
pyttop/plot/plotfuncs.py
pyttop/sampledata/__init__.py
pyttop/sampledata/base.py
pyttop/sampledata/gen.py
pyttop/sampledata/get.py
pyttop/sampledata/lgm.py
pyttop/table/__init__.py
pyttop/table/exceptions.py
pyttop/table/operations.py
pyttop/table/table.py
pyttop/ui/base.py
pyttop-0.4.4.dist-info/licenses/LICENSE
pyttop-0.4.4.dist-info/METADATA
pyttop-0.4.4.dist-info/WHEEL
pyttop-0.4.4.dist-info/top_level.txt
pyttop-0.4.4.dist-info/RECORD
