Metadata-Version: 2.4
Name: pyttop
Version: 0.4.4
Summary: Python Tools for Table Operations and Plotting
Author: Yu-Chen Wang
License: GPL-3.0-only
Project-URL: Documentation, https://pyttop.readthedocs.io/
Project-URL: Repository, https://github.com/ycwang-astro/pyttop.git
Project-URL: Issues, https://github.com/ycwang-astro/pyttop/issues
Keywords: table,table operation,catalog matching,catalog merging,table matching,table merging,plot,scientific plot,row subset
Classifier: Development Status :: 4 - Beta
Classifier: Programming Language :: Python :: 3
Classifier: License :: OSI Approved :: GNU General Public License v3 (GPLv3)
Classifier: Intended Audience :: Science/Research
Requires-Python: >=3.8
License-File: LICENSE
Requires-Dist: astropy
Requires-Dist: matplotlib
Requires-Dist: numpy
Dynamic: license-file
